flexlogger/automation/__init__.py
flexlogger/automation/_application.py
flexlogger/automation/_channel_data_point.py
flexlogger/automation/_channel_specification_document.py
flexlogger/automation/_data_rate_level.py
flexlogger/automation/_event_names.py
flexlogger/automation/_event_payloads.py
flexlogger/automation/_event_type.py
flexlogger/automation/_events.py
flexlogger/automation/_flexlogger_error.py
flexlogger/automation/_log_file_type.py
flexlogger/automation/_logging_specification_document.py
flexlogger/automation/_project.py
flexlogger/automation/_screen_document.py
flexlogger/automation/_severity_level.py
flexlogger/automation/_start_trigger_condition.py
flexlogger/automation/_stop_trigger_condition.py
flexlogger/automation/_test_property.py
flexlogger/automation/_test_session.py
flexlogger/automation/_test_session_state.py
flexlogger/automation/_test_specification_document.py
flexlogger/automation/_value_change_condition.py
flexlogger/automation/_value_change_type.py
flexlogger/automation/proto/Application_pb2.py
flexlogger/automation/proto/Application_pb2_grpc.py
flexlogger/automation/proto/AutomationClientType_pb2.py
flexlogger/automation/proto/AutomationClientType_pb2_grpc.py
flexlogger/automation/proto/ChannelSpecificationDocument_pb2.py
flexlogger/automation/proto/ChannelSpecificationDocument_pb2_grpc.py
flexlogger/automation/proto/DataRateLevel_pb2.py
flexlogger/automation/proto/DataRateLevel_pb2_grpc.py
flexlogger/automation/proto/Document_pb2.py
flexlogger/automation/proto/Document_pb2_grpc.py
flexlogger/automation/proto/EventType_pb2.py
flexlogger/automation/proto/EventType_pb2_grpc.py
flexlogger/automation/proto/Events_pb2.py
flexlogger/automation/proto/Events_pb2_grpc.py
flexlogger/automation/proto/FlexLoggerApplication_pb2.py
flexlogger/automation/proto/FlexLoggerApplication_pb2_grpc.py
flexlogger/automation/proto/Identifiers_pb2.py
flexlogger/automation/proto/Identifiers_pb2_grpc.py
flexlogger/automation/proto/Log_pb2.py
niflexlogger_automation-0.2.4.dist-info/licenses/LICENSE
niflexlogger_automation-0.2.4.dist-info/METADATA
niflexlogger_automation-0.2.4.dist-info/WHEEL
niflexlogger_automation-0.2.4.dist-info/top_level.txt
niflexlogger_automation-0.2.4.dist-info/RECORD
