Metadata-Version: 2.4
Name: niflexlogger-automation
Version: 0.2.4
Summary: NI FlexLogger Python API
Author: National Instruments
Maintainer: Ben Parrott, Greg Stoll
Maintainer-email: ben.parrott@ni.com, greg.stoll@ni.com
License: MIT
Keywords: niflexlogger,flexlogger
Classifier: Development Status :: 5 - Production/Stable
Classifier: Intended Audience :: Developers
Classifier: Intended Audience :: Manufacturing
Classifier: Intended Audience :: Science/Research
Classifier: License :: OSI Approved :: MIT License
Classifier: Operating System :: Microsoft :: Windows
Classifier: Programming Language :: Python :: 3.6
Classifier: Programming Language :: Python :: 3.7
Classifier: Programming Language :: Python :: 3.8
Classifier: Programming Language :: Python :: 3.9
Classifier: Programming Language :: Python :: 3.10
Classifier: Programming Language :: Python :: 3.11
Classifier: Programming Language :: Python :: 3.12
Classifier: Programming Language :: Python :: 3.13
Classifier: Programming Language :: Python :: Implementation :: CPython
Classifier: Topic :: Scientific/Engineering
Classifier: Topic :: System :: Hardware
License-File: LICENSE
Requires-Dist: typing-extensions
Requires-Dist: grpcio
Requires-Dist: grpcio-tools
Requires-Dist: psutil
Requires-Dist: pywin32; platform_system == "Windows"
Requires-Dist: console-menu
Requires-Dist: PrettyTable
Requires-Dist: python-dateutil
Dynamic: author
Dynamic: classifier
Dynamic: description
Dynamic: keywords
Dynamic: license
Dynamic: license-file
Dynamic: maintainer
Dynamic: maintainer-email
Dynamic: requires-dist
Dynamic: summary
